casbin_redis_watcher/__init__.py
casbin_redis_watcher/options.py
casbin_redis_watcher/watcher.py
tests/__init__.py
tests/test_redis_watcher.py
test_test782764782642-1.3.0.dist-info/LICENSE
test_test782764782642-1.3.0.dist-info/METADATA
test_test782764782642-1.3.0.dist-info/WHEEL
test_test782764782642-1.3.0.dist-info/top_level.txt
test_test782764782642-1.3.0.dist-info/RECORD
